CHANGES.rst
LICENSE
MANIFEST.in
README.rst
setup.py
mozcpy/__init__.py
mozcpy/mozcpy.py
mozcpy.egg-info/PKG-INFO
mozcpy.egg-info/SOURCES.txt
mozcpy.egg-info/dependency_links.txt
mozcpy.egg-info/requires.txt
mozcpy.egg-info/top_level.txt
mozcpy/dic/char.bin
mozcpy/dic/char.def
mozcpy/dic/dicrc
mozcpy/dic/matrix.bin
mozcpy/dic/rewrite.def
mozcpy/dic/sys.dic
mozcpy/dic/unk.def
mozcpy/dic/unk.dic