Metadata-Version: 2.1
Name: mozcpy
Version: 0.2
Summary: Mozc for Python: yet another Kana-Kanji converter
Home-page: https://github.com/ikegami-yukino/mozcpy
Author: Yukino Ikegami
Author-email: yknikgm@gmail.com
License: MIT License
Keywords: Kana-Kanji converter
Platform: POSIX
Platform: Windows
Platform: Unix
Platform: MacOS
Classifier: Development Status :: 3 - Alpha
Classifier: Intended Audience :: Developers
Classifier: Intended Audience :: Information Technology
Classifier: License :: OSI Approved :: MIT License
Classifier: Natural Language :: Japanese
Classifier: Programming Language :: Python :: 3.4
Classifier: Programming Language :: Python :: 3.5
Classifier: Programming Language :: Python :: 3.6
Classifier: Programming Language :: Python :: 3.7
Classifier: Programming Language :: Python :: 3.8
Classifier: Programming Language :: Python :: 3.9
Classifier: Programming Language :: Python :: 3.10
Classifier: Programming Language :: Python :: 3.11
Classifier: Programming Language :: Python :: 3.12
Classifier: Topic :: Text Processing :: Linguistic
License-File: LICENSE
Requires-Dist: mecab
